Workbook

Sheet Dataset
A1: Product_ID | B1: Sale_Date | C1: Sales_Rep | D1: Region | E1: Sales_Amount | F1: Quantity_Sold | G1: Product_Category | H1: Unit_Cost | I1: Unit_Price | J1: Customer_Type | K1: Discount | L1: Payment_Method | M1: Sales_Channel | N1: Region_and_Sales_Rep | O1: Month | P1: Month number | Q1: Year
A2: 1052 | B2: 44960 | C2: Bob | D2: North | E2: 5053.97 | F2: 18 | G2: Furniture | H2: 152.75 | I2: 267.22 | J2: Returning | K2: 0.09 | L2: Cash | M2: Online | N2: North-Bob | O2: =TEXT(B2,"mmmm") -> February | P2: 2 | Q2: =YEAR(B2) -> 2023
A3: 1093 | B3: 45037 | C3: Bob | D3: West | E3: 4384.02 | F3: 17 | G3: Furniture | H3: 3816.39 | I3: 4209.44 | J3: Returning | K3: 0.11 | L3: Cash | M3: Retail | N3: West-Bob | O3: =TEXT(B3,"mmmm") -> April | P3: =MONTH(B3) -> 4 | Q3: =YEAR(B3) -> 2023
A4: 1015 | B4: 45190 | C4: David | D4: South | E4: 4631.23 | F4: 30 | G4: Food | H4: 261.56 | I4: 371.4 | J4: Returning | K4: 0.2 | L4: Bank Transfer | M4: Retail | N4: South-David | O4: =TEXT(B4,"mmmm") -> September | P4: =MONTH(B4) -> 9 | Q4: =YEAR(B4) -> 2023
A5: 1072 | B5: 45162 | C5: Bob | D5: South | E5: 2167.94 | F5: 39 | G5: Clothing | H5: 4330.03 | I5: 4467.75 | J5: New | K5: 0.02 | L5: Credit Card | M5: Retail | N5: South-Bob | O5: =TEXT(B5,"mmmm") -> August | P5: =MONTH(B5) -> 8 | Q5: =YEAR(B5) -> 2023
A6: 1061 | B6: 45009 | C6: Charlie | D6: East | E6: 3750.2 | F6: 13 | G6: Electronics | H6: 637.37 | I6: 692.71 | J6: New | K6: 0.08 | L6: Credit Card | M6: Online | N6: East-Charlie | O6: =TEXT(B6,"mmmm") -> March | P6: =MONTH(B6) -> 3 | Q6: =YEAR(B6) -> 2023
A7: 1021 | B7: 44968 | C7: Charlie | D7: West | E7: 3761.15 | F7: 32 | G7: Food | H7: 900.79 | I7: 1106.51 | J7: New | K7: 0.21 | L7: Cash | M7: Online | N7: West-Charlie | O7: =TEXT(B7,"mmmm") -> February | P7: =MONTH(B7) -> 2 | Q7: =YEAR(B7) -> 2023
A8: 1083 | B8: 45027 | C8: Bob | D8: West | E8: 618.31 | F8: 29 | G8: Furniture | H8: 2408.81 | I8: 2624.09 | J8: Returning | K8: 0.14 | L8: Cash | M8: Online | N8: West-Bob | O8: =TEXT(B8,"mmmm") -> April | P8: =MONTH(B8) -> 4 | Q8: =YEAR(B8) -> 2023
A9: 1087 | B9: 44932 | C9: Eve | D9: South | E9: 7698.92 | F9: 46 | G9: Furniture | H9: 3702.51 | I9: 3964.65 | J9: New | K9: 0.12 | L9: Bank Transfer | M9: Online | N9: South-Eve | O9: =TEXT(B9,"mmmm") -> January | P9: =MONTH(B9) -> 1 | Q9: =YEAR(B9) -> 2023
A10: 1075 | B10: 45106 | C10: David | D10: South | E10: 4223.39 | F10: 30 | G10: Furniture | H10: 738.06 | I10: 1095.45 | J10: New | K10: 0.05 | L10: Bank Transfer | M10: Online | N10: South-David | O10: =TEXT(B10,"mmmm") -> June | P10: =MONTH(B10) -> 6 | Q10: =YEAR(B10) -> 2023
A11: 1075 | B11: 45208 | C11: Charlie | D11: West | E11: 8239.58 | F11: 18 | G11: Clothing | H11: 2228.35 | I11: 2682.34 | J11: New | K11: 0.13 | L11: Bank Transfer | M11: Online | N11: West-Charlie | O11: =TEXT(B11,"mmmm") -> October | P11: =MONTH(B11) -> 10 | Q11: =YEAR(B11) -> 2023
A12: 1088 | B12: 45246 | C12: Eve | D12: North | E12: 8518.45 | F12: 13 | G12: Furniture | H12: 2440.11 | I12: 2517.6 | J12: New | K12: 0.23 | L12: Bank Transfer | M12: Retail | N12: North-Eve | O12: =TEXT(B12,"mmmm") -> November | P12: =MONTH(B12) -> 11 | Q12: =YEAR(B12) -> 2023
A13: 1100 | B13: 45152 | C13: Bob | D13: West | E13: 2198.74 | F13: 43 | G13: Food | H13: 1100.81 | I13: 1137.44 | J13: Returning | K13: 0.08 | L13: Bank Transfer | M13: Online | N13: West-Bob | O13: =TEXT(B13,"mmmm") -> August | P13: =MONTH(B13) -> 8 | Q13: =YEAR(B13) -> 2023
A14: 1024 | B14: 45241 | C14: Eve | D14: West | E14: 6607.8 | F14: 21 | G14: Food | H14: 622.01 | I14: 641.09 | J14: Returning | K14: 0 | L14: Bank Transfer | M14: Retail | N14: West-Eve | O14: =TEXT(B14,"mmmm") -> November | P14: =MONTH(B14) -> 11 | Q14: =YEAR(B14) -> 2023
... A1001: 1086 | B1001: 45154 | C1001: Alice | D1001: East | E1001: 4923.93 | F1001: 48 | G1001: Food | H1001: 2632.58 | I1001: 2926.68 | J1001: Returning | K1001: 0.14 | L1001: Cash | M1001: Online | N1001: East-Alice | O1001: =TEXT(B1001,"mmmm") -> August | P1001: =MONTH(B1001) -> 8 | Q1001: =YEAR(B1001) -> 2023

Sheet Summary_Analysis
A1: Total Sales | B1: Total Quantity | C1: Average Sale | D1: Maximum Sale | E1: Minimum Sale | F1: Total Transactions
A2: =SUM(Dataset!E:E) -> 5019265.2 | B2: =SUM(Dataset!F:F) -> 25355 | C2: =AVERAGE(Dataset!E:E) -> 5019.2652 | D2: =MAX(Dataset!E:E) -> 9989.04 | E2: =MIN(Dataset!E:E) -> 100.12 | F2: =COUNTA(Dataset!A:A)-1 -> 1000
A7: Months | B7: Total Sales | D7: Region | E7: Total Sales | G7: Products category | H7: Total Sales
A8: January | B8: 495420.37 | D8: North | E8: 1369612.5 | G8: Clothing | H8: 1313474.4
A9: February | B9: 368919.36 | D9: East | E9: 1259792.9 | G9: Furniture | H9: 1260517.7
A10: March | B10: 402638.77 | D10: West | E10: 1235608.9 | G10: Electronics | H10: 1243499.6
A11: April | B11: 438992.61 | D11: South | E11: 1154250.9 | G11: Food | H11: 1201773.5
A12: May | B12: 389078.76 | D12: Grand Total | E12: 5019265.2 | G12: Grand Total | H12: 5019265.2
A13: June | B13: 418458.34
A14: July | B14: 374242.88
A15: August | B15: 443171.28 | D15: Sales Rep | E15: Total Sales | G15: Customer Type | H15: Total Sales
A16: September | B16: 367837.6 | D16: David | E16: 1141737.4 | G16: Returning | H16: 2513006.9
A17: October | B17: 460378.78 | D17: Bob | E17: 1080990.6 | G17: New | H17: 2506258.3
A18: November | B18: 467482.9 | D18: Eve | E18: 970183.99 | G18: Grand Total | H18: 5019265.2
A19: December | B19: 392643.58 | D19: Alice | E19: 965541.77
A20: Grand Total | B20: 5019265.2 | D20: Charlie | E20: 860811.48
D21: Grand Total | E21: 5019265.2
